README.md
setup.cfg
setup.py
celebrities_births_100/__init__.py
celebrities_births_100/__main__.py
celebrities_births_100/date.py
celebrities_births_100/scraper.py
celebrity_births_100.egg-info/PKG-INFO
celebrity_births_100.egg-info/SOURCES.txt
celebrity_births_100.egg-info/dependency_links.txt
celebrity_births_100.egg-info/requires.txt
celebrity_births_100.egg-info/top_level.txt
test/__init__.py
test/test_celebrities_births.py
test/test_date.py
test/test_scraper.py