Metadata-Version: 1.0
Name: celebrity-births-100
Version: 0.0.1
Summary: Mock package that allows you to find celebrity by date of birth
Home-page: https://github.com/ovidiu100/Celebrities-Births
Author: Ovidiu Popa
Author-email: UNKNOWN
License: MIT
Platform: UNKNOWN
